sqlagg/__init__.py
sqlagg/base.py
sqlagg/columns.py
sqlagg/exceptions.py
sqlagg/filters.py
sqlagg/sorting.py
sqlagg-0.18.0.dist-info/licenses/LICENSE
sqlagg-0.18.0.dist-info/WHEEL
sqlagg-0.18.0.dist-info/METADATA
sqlagg-0.18.0.dist-info/RECORD
