Metadata-Version: 2.4
Name: sqlagg
Version: 0.18.0
Summary: SQL aggregation tool
Author-email: Dimagi <dev@dimagi.com>
Requires-Python: >= 3.9
Classifier: Intended Audience :: Developers
Classifier: License :: OSI Approved :: MIT License
Classifier: Programming Language :: Python :: 3
Classifier: Programming Language :: Python :: 3.9
Classifier: Programming Language :: Python :: 3.10
Classifier: Programming Language :: Python :: 3.11
Classifier: Programming Language :: Python :: 3.12
Classifier: Programming Language :: Python :: 3.13
License-File: LICENSE
Requires-Dist: SQLAlchemy>=1.0.9,<1.4
Requires-Dist: SQLAlchemy-Fixtures>=0.1.5 ; extra == "test"
Requires-Dist: pytest ; extra == "test"
Requires-Dist: pytest-unmagic ; extra == "test"
Requires-Dist: psycopg2-binary ; extra == "test"
Project-URL: Home, https://github.com/dimagi/sql-agg
Provides-Extra: test
